[
  {
    "id": 1061040738,
    "node_id": "R_kgDOPz4yYg",
    "name": "ai-hoops-board",
    "full_name": "charlie2233/ai-hoops-board",
    "private": false,
    "owner": {
      "login": "charlie2233",
      "id": 117957000,
      "node_id": "U_kgDOBwfhiA",
      "avatar_url": "https://avatars.githubusercontent.com/u/117957000?v=4",
      "gravatar_id": "",
      "url": "https://api.github.com/users/charlie2233",
      "html_url": "https://github.com/charlie2233",
      "followers_url": "https://api.github.com/users/charlie2233/followers",
      "following_url": "https://api.github.com/users/charlie2233/following{/other_user}",
      "gists_url": "https://api.github.com/users/charlie2233/gists{/gist_id}",
      "starred_url": "https://api.github.com/users/charlie2233/starred{/owner}{/repo}",
      "subscriptions_url": "https://api.github.com/users/charlie2233/subscriptions",
      "organizations_url": "https://api.github.com/users/charlie2233/orgs",
      "repos_url": "https://api.github.com/users/charlie2233/repos",
      "events_url": "https://api.github.com/users/charlie2233/events{/privacy}",
      "received_events_url": "https://api.github.com/users/charlie2233/received_events",
      "type": "User",
      "user_view_type": "public",
      "site_admin": false
    },
    "html_url": "https://github.com/charlie2233/ai-hoops-board",
    "description": "ai-hoops-board",
    "fork": false,
    "url": "https://api.github.com/repos/charlie2233/ai-hoops-board",
    "forks_url": "https://api.github.com/repos/charlie2233/ai-hoops-board/forks",
    "keys_url": "https://api.github.com/repos/charlie2233/ai-hoops-board/keys{/key_id}",
    "collaborators_url": "https://api.github.com/repos/charlie2233/ai-hoops-board/collaborators{/collaborator}",
    "teams_url": "https://api.github.com/repos/charlie2233/ai-hoops-board/teams",
    "hooks_url": "https://api.github.com/repos/charlie2233/ai-hoops-board/hooks",
    "issue_events_url": "https://api.github.com/repos/charlie2233/ai-hoops-board/issues/events{/number}",
    "events_url": "https://api.github.com/repos/charlie2233/ai-hoops-board/events",
    "assignees_url": "https://api.github.com/repos/charlie2233/ai-hoops-board/assignees{/user}",
    "branches_url": "https://api.github.com/repos/charlie2233/ai-hoops-board/branches{/branch}",
    "tags_url": "https://api.github.com/repos/charlie2233/ai-hoops-board/tags",
    "blobs_url": "https://api.github.com/repos/charlie2233/ai-hoops-board/git/blobs{/sha}",
    "git_tags_url": "https://api.github.com/repos/charlie2233/ai-hoops-board/git/tags{/sha}",
    "git_refs_url": "https://api.github.com/repos/charlie2233/ai-hoops-board/git/refs{/sha}",
    "trees_url": "https://api.github.com/repos/charlie2233/ai-hoops-board/git/trees{/sha}",
    "statuses_url": "https://api.github.com/repos/charlie2233/ai-hoops-board/statuses/{sha}",
    "languages_url": "https://api.github.com/repos/charlie2233/ai-hoops-board/languages",
    "stargazers_url": "https://api.github.com/repos/charlie2233/ai-hoops-board/stargazers",
    "contributors_url": "https://api.github.com/repos/charlie2233/ai-hoops-board/contributors",
    "subscribers_url": "https://api.github.com/repos/charlie2233/ai-hoops-board/subscribers",
    "subscription_url": "https://api.github.com/repos/charlie2233/ai-hoops-board/subscription",
    "commits_url": "https://api.github.com/repos/charlie2233/ai-hoops-board/commits{/sha}",
    "git_commits_url": "https://api.github.com/repos/charlie2233/ai-hoops-board/git/commits{/sha}",
    "comments_url": "https://api.github.com/repos/charlie2233/ai-hoops-board/comments{/number}",
    "issue_comment_url": "https://api.github.com/repos/charlie2233/ai-hoops-board/issues/comments{/number}",
    "contents_url": "https://api.github.com/repos/charlie2233/ai-hoops-board/contents/{+path}",
    "compare_url": "https://api.github.com/repos/charlie2233/ai-hoops-board/compare/{base}...{head}",
    "merges_url": "https://api.github.com/repos/charlie2233/ai-hoops-board/merges",
    "archive_url": "https://api.github.com/repos/charlie2233/ai-hoops-board/{archive_format}{/ref}",
    "downloads_url": "https://api.github.com/repos/charlie2233/ai-hoops-board/downloads",
    "issues_url": "https://api.github.com/repos/charlie2233/ai-hoops-board/issues{/number}",
    "pulls_url": "https://api.github.com/repos/charlie2233/ai-hoops-board/pulls{/number}",
    "milestones_url": "https://api.github.com/repos/charlie2233/ai-hoops-board/milestones{/number}",
    "notifications_url": "https://api.github.com/repos/charlie2233/ai-hoops-board/notifications{?since,all,participating}",
    "labels_url": "https://api.github.com/repos/charlie2233/ai-hoops-board/labels{/name}",
    "releases_url": "https://api.github.com/repos/charlie2233/ai-hoops-board/releases{/id}",
    "deployments_url": "https://api.github.com/repos/charlie2233/ai-hoops-board/deployments",
    "created_at": "2025-09-21T05:43:27Z",
    "updated_at": "2026-02-03T07:11:06Z",
    "pushed_at": "2025-10-15T16:55:57Z",
    "git_url": "git://github.com/charlie2233/ai-hoops-board.git",
    "ssh_url": "git@github.com:charlie2233/ai-hoops-board.git",
    "clone_url": "https://github.com/charlie2233/ai-hoops-board.git",
    "svn_url": "https://github.com/charlie2233/ai-hoops-board",
    "homepage": null,
    "size": 217,
    "stargazers_count": 0,
    "watchers_count": 0,
    "language": "JavaScript",
    "has_issues": true,
    "has_projects": true,
    "has_downloads": true,
    "has_wiki": false,
    "has_pages": true,
    "has_discussions": false,
    "forks_count": 0,
    "mirror_url": null,
    "archived": false,
    "disabled": false,
    "open_issues_count": 0,
    "license": {
      "key": "mit",
      "name": "MIT License",
      "spdx_id": "MIT",
      "url": "https://api.github.com/licenses/mit",
      "node_id": "MDc6TGljZW5zZTEz"
    },
    "allow_forking": true,
    "is_template": false,
    "web_commit_signoff_required": false,
    "topics": [

    ],
    "visibility": "public",
    "forks": 0,
    "open_issues": 0,
    "watchers": 0,
    "default_branch": "main",
    "permissions": {
      "admin": true,
      "maintain": true,
      "push": true,
      "triage": true,
      "pull": true
    }
  },
  {
    "id": 1133081515,
    "node_id": "R_kgDOQ4lzqw",
    "name": "rork-ten-seconds-vip-manager",
    "full_name": "charlie2233/rork-ten-seconds-vip-manager",
    "private": false,
    "owner": {
      "login": "charlie2233",
      "id": 117957000,
      "node_id": "U_kgDOBwfhiA",
      "avatar_url": "https://avatars.githubusercontent.com/u/117957000?v=4",
      "gravatar_id": "",
      "url": "https://api.github.com/users/charlie2233",
      "html_url": "https://github.com/charlie2233",
      "followers_url": "https://api.github.com/users/charlie2233/followers",
      "following_url": "https://api.github.com/users/charlie2233/following{/other_user}",
      "gists_url": "https://api.github.com/users/charlie2233/gists{/gist_id}",
      "starred_url": "https://api.github.com/users/charlie2233/starred{/owner}{/repo}",
      "subscriptions_url": "https://api.github.com/users/charlie2233/subscriptions",
      "organizations_url": "https://api.github.com/users/charlie2233/orgs",
      "repos_url": "https://api.github.com/users/charlie2233/repos",
      "events_url": "https://api.github.com/users/charlie2233/events{/privacy}",
      "received_events_url": "https://api.github.com/users/charlie2233/received_events",
      "type": "User",
      "user_view_type": "public",
      "site_admin": false
    },
    "html_url": "https://github.com/charlie2233/rork-ten-seconds-vip-manager",
    "description": "Created by Rork",
    "fork": false,
    "url": "https://api.github.com/repos/charlie2233/rork-ten-seconds-vip-manager",
    "forks_url": "https://api.github.com/repos/charlie2233/rork-ten-seconds-vip-manager/forks",
    "keys_url": "https://api.github.com/repos/charlie2233/rork-ten-seconds-vip-manager/keys{/key_id}",
    "collaborators_url": "https://api.github.com/repos/charlie2233/rork-ten-seconds-vip-manager/collaborators{/collaborator}",
    "teams_url": "https://api.github.com/repos/charlie2233/rork-ten-seconds-vip-manager/teams",
    "hooks_url": "https://api.github.com/repos/charlie2233/rork-ten-seconds-vip-manager/hooks",
    "issue_events_url": "https://api.github.com/repos/charlie2233/rork-ten-seconds-vip-manager/issues/events{/number}",
    "events_url": "https://api.github.com/repos/charlie2233/rork-ten-seconds-vip-manager/events",
    "assignees_url": "https://api.github.com/repos/charlie2233/rork-ten-seconds-vip-manager/assignees{/user}",
    "branches_url": "https://api.github.com/repos/charlie2233/rork-ten-seconds-vip-manager/branches{/branch}",
    "tags_url": "https://api.github.com/repos/charlie2233/rork-ten-seconds-vip-manager/tags",
    "blobs_url": "https://api.github.com/repos/charlie2233/rork-ten-seconds-vip-manager/git/blobs{/sha}",
    "git_tags_url": "https://api.github.com/repos/charlie2233/rork-ten-seconds-vip-manager/git/tags{/sha}",
    "git_refs_url": "https://api.github.com/repos/charlie2233/rork-ten-seconds-vip-manager/git/refs{/sha}",
    "trees_url": "https://api.github.com/repos/charlie2233/rork-ten-seconds-vip-manager/git/trees{/sha}",
    "statuses_url": "https://api.github.com/repos/charlie2233/rork-ten-seconds-vip-manager/statuses/{sha}",
    "languages_url": "https://api.github.com/repos/charlie2233/rork-ten-seconds-vip-manager/languages",
    "stargazers_url": "https://api.github.com/repos/charlie2233/rork-ten-seconds-vip-manager/stargazers",
    "contributors_url": "https://api.github.com/repos/charlie2233/rork-ten-seconds-vip-manager/contributors",
    "subscribers_url": "https://api.github.com/repos/charlie2233/rork-ten-seconds-vip-manager/subscribers",
    "subscription_url": "https://api.github.com/repos/charlie2233/rork-ten-seconds-vip-manager/subscription",
    "commits_url": "https://api.github.com/repos/charlie2233/rork-ten-seconds-vip-manager/commits{/sha}",
    "git_commits_url": "https://api.github.com/repos/charlie2233/rork-ten-seconds-vip-manager/git/commits{/sha}",
    "comments_url": "https://api.github.com/repos/charlie2233/rork-ten-seconds-vip-manager/comments{/number}",
    "issue_comment_url": "https://api.github.com/repos/charlie2233/rork-ten-seconds-vip-manager/issues/comments{/number}",
    "contents_url": "https://api.github.com/repos/charlie2233/rork-ten-seconds-vip-manager/contents/{+path}",
    "compare_url": "https://api.github.com/repos/charlie2233/rork-ten-seconds-vip-manager/compare/{base}...{head}",
    "merges_url": "https://api.github.com/repos/charlie2233/rork-ten-seconds-vip-manager/merges",
    "archive_url": "https://api.github.com/repos/charlie2233/rork-ten-seconds-vip-manager/{archive_format}{/ref}",
    "downloads_url": "https://api.github.com/repos/charlie2233/rork-ten-seconds-vip-manager/downloads",
    "issues_url": "https://api.github.com/repos/charlie2233/rork-ten-seconds-vip-manager/issues{/number}",
    "pulls_url": "https://api.github.com/repos/charlie2233/rork-ten-seconds-vip-manager/pulls{/number}",
    "milestones_url": "https://api.github.com/repos/charlie2233/rork-ten-seconds-vip-manager/milestones{/number}",
    "notifications_url": "https://api.github.com/repos/charlie2233/rork-ten-seconds-vip-manager/notifications{?since,all,participating}",
    "labels_url": "https://api.github.com/repos/charlie2233/rork-ten-seconds-vip-manager/labels{/name}",
    "releases_url": "https://api.github.com/repos/charlie2233/rork-ten-seconds-vip-manager/releases{/id}",
    "deployments_url": "https://api.github.com/repos/charlie2233/rork-ten-seconds-vip-manager/deployments",
    "created_at": "2026-01-12T21:22:21Z",
    "updated_at": "2026-01-23T07:48:34Z",
    "pushed_at": "2026-01-23T07:48:30Z",
    "git_url": "git://github.com/charlie2233/rork-ten-seconds-vip-manager.git",
    "ssh_url": "git@github.com:charlie2233/rork-ten-seconds-vip-manager.git",
    "clone_url": "https://github.com/charlie2233/rork-ten-seconds-vip-manager.git",
    "svn_url": "https://github.com/charlie2233/rork-ten-seconds-vip-manager",
    "homepage": null,
    "size": 124487,
    "stargazers_count": 0,
    "watchers_count": 0,
    "language": "TypeScript",
    "has_issues": true,
    "has_projects": true,
    "has_downloads": true,
    "has_wiki": true,
    "has_pages": false,
    "has_discussions": false,
    "forks_count": 0,
    "mirror_url": null,
    "archived": false,
    "disabled": false,
    "open_issues_count": 0,
    "license": null,
    "allow_forking": true,
    "is_template": false,
    "web_commit_signoff_required": false,
    "topics": [

    ],
    "visibility": "public",
    "forks": 0,
    "open_issues": 0,
    "watchers": 0,
    "default_branch": "main",
    "permissions": {
      "admin": true,
      "maintain": true,
      "push": true,
      "triage": true,
      "pull": true
    }
  },
  {
    "id": 1101568155,
    "node_id": "R_kgDOQaiYmw",
    "name": "rork-guide-pup--vision-assistant",
    "full_name": "charlie2233/rork-guide-pup--vision-assistant",
    "private": false,
    "owner": {
      "login": "charlie2233",
      "id": 117957000,
      "node_id": "U_kgDOBwfhiA",
      "avatar_url": "https://avatars.githubusercontent.com/u/117957000?v=4",
      "gravatar_id": "",
      "url": "https://api.github.com/users/charlie2233",
      "html_url": "https://github.com/charlie2233",
      "followers_url": "https://api.github.com/users/charlie2233/followers",
      "following_url": "https://api.github.com/users/charlie2233/following{/other_user}",
      "gists_url": "https://api.github.com/users/charlie2233/gists{/gist_id}",
      "starred_url": "https://api.github.com/users/charlie2233/starred{/owner}{/repo}",
      "subscriptions_url": "https://api.github.com/users/charlie2233/subscriptions",
      "organizations_url": "https://api.github.com/users/charlie2233/orgs",
      "repos_url": "https://api.github.com/users/charlie2233/repos",
      "events_url": "https://api.github.com/users/charlie2233/events{/privacy}",
      "received_events_url": "https://api.github.com/users/charlie2233/received_events",
      "type": "User",
      "user_view_type": "public",
      "site_admin": false
    },
    "html_url": "https://github.com/charlie2233/rork-guide-pup--vision-assistant",
    "description": "Created by Rork",
    "fork": false,
    "url": "https://api.github.com/repos/charlie2233/rork-guide-pup--vision-assistant",
    "forks_url": "https://api.github.com/repos/charlie2233/rork-guide-pup--vision-assistant/forks",
    "keys_url": "https://api.github.com/repos/charlie2233/rork-guide-pup--vision-assistant/keys{/key_id}",
    "collaborators_url": "https://api.github.com/repos/charlie2233/rork-guide-pup--vision-assistant/collaborators{/collaborator}",
    "teams_url": "https://api.github.com/repos/charlie2233/rork-guide-pup--vision-assistant/teams",
    "hooks_url": "https://api.github.com/repos/charlie2233/rork-guide-pup--vision-assistant/hooks",
    "issue_events_url": "https://api.github.com/repos/charlie2233/rork-guide-pup--vision-assistant/issues/events{/number}",
    "events_url": "https://api.github.com/repos/charlie2233/rork-guide-pup--vision-assistant/events",
    "assignees_url": "https://api.github.com/repos/charlie2233/rork-guide-pup--vision-assistant/assignees{/user}",
    "branches_url": "https://api.github.com/repos/charlie2233/rork-guide-pup--vision-assistant/branches{/branch}",
    "tags_url": "https://api.github.com/repos/charlie2233/rork-guide-pup--vision-assistant/tags",
    "blobs_url": "https://api.github.com/repos/charlie2233/rork-guide-pup--vision-assistant/git/blobs{/sha}",
    "git_tags_url": "https://api.github.com/repos/charlie2233/rork-guide-pup--vision-assistant/git/tags{/sha}",
    "git_refs_url": "https://api.github.com/repos/charlie2233/rork-guide-pup--vision-assistant/git/refs{/sha}",
    "trees_url": "https://api.github.com/repos/charlie2233/rork-guide-pup--vision-assistant/git/trees{/sha}",
    "statuses_url": "https://api.github.com/repos/charlie2233/rork-guide-pup--vision-assistant/statuses/{sha}",
    "languages_url": "https://api.github.com/repos/charlie2233/rork-guide-pup--vision-assistant/languages",
    "stargazers_url": "https://api.github.com/repos/charlie2233/rork-guide-pup--vision-assistant/stargazers",
    "contributors_url": "https://api.github.com/repos/charlie2233/rork-guide-pup--vision-assistant/contributors",
    "subscribers_url": "https://api.github.com/repos/charlie2233/rork-guide-pup--vision-assistant/subscribers",
    "subscription_url": "https://api.github.com/repos/charlie2233/rork-guide-pup--vision-assistant/subscription",
    "commits_url": "https://api.github.com/repos/charlie2233/rork-guide-pup--vision-assistant/commits{/sha}",
    "git_commits_url": "https://api.github.com/repos/charlie2233/rork-guide-pup--vision-assistant/git/commits{/sha}",
    "comments_url": "https://api.github.com/repos/charlie2233/rork-guide-pup--vision-assistant/comments{/number}",
    "issue_comment_url": "https://api.github.com/repos/charlie2233/rork-guide-pup--vision-assistant/issues/comments{/number}",
    "contents_url": "https://api.github.com/repos/charlie2233/rork-guide-pup--vision-assistant/contents/{+path}",
    "compare_url": "https://api.github.com/repos/charlie2233/rork-guide-pup--vision-assistant/compare/{base}...{head}",
    "merges_url": "https://api.github.com/repos/charlie2233/rork-guide-pup--vision-assistant/merges",
    "archive_url": "https://api.github.com/repos/charlie2233/rork-guide-pup--vision-assistant/{archive_format}{/ref}",
    "downloads_url": "https://api.github.com/repos/charlie2233/rork-guide-pup--vision-assistant/downloads",
    "issues_url": "https://api.github.com/repos/charlie2233/rork-guide-pup--vision-assistant/issues{/number}",
    "pulls_url": "https://api.github.com/repos/charlie2233/rork-guide-pup--vision-assistant/pulls{/number}",
    "milestones_url": "https://api.github.com/repos/charlie2233/rork-guide-pup--vision-assistant/milestones{/number}",
    "notifications_url": "https://api.github.com/repos/charlie2233/rork-guide-pup--vision-assistant/notifications{?since,all,participating}",
    "labels_url": "https://api.github.com/repos/charlie2233/rork-guide-pup--vision-assistant/labels{/name}",
    "releases_url": "https://api.github.com/repos/charlie2233/rork-guide-pup--vision-assistant/releases{/id}",
    "deployments_url": "https://api.github.com/repos/charlie2233/rork-guide-pup--vision-assistant/deployments",
    "created_at": "2025-11-21T21:37:16Z",
    "updated_at": "2026-01-19T00:06:58Z",
    "pushed_at": "2026-01-11T08:11:12Z",
    "git_url": "git://github.com/charlie2233/rork-guide-pup--vision-assistant.git",
    "ssh_url": "git@github.com:charlie2233/rork-guide-pup--vision-assistant.git",
    "clone_url": "https://github.com/charlie2233/rork-guide-pup--vision-assistant.git",
    "svn_url": "https://github.com/charlie2233/rork-guide-pup--vision-assistant",
    "homepage": null,
    "size": 7748,
    "stargazers_count": 0,
    "watchers_count": 0,
    "language": "TypeScript",
    "has_issues": true,
    "has_projects": true,
    "has_downloads": true,
    "has_wiki": true,
    "has_pages": false,
    "has_discussions": false,
    "forks_count": 0,
    "mirror_url": null,
    "archived": false,
    "disabled": false,
    "open_issues_count": 0,
    "license": null,
    "allow_forking": true,
    "is_template": false,
    "web_commit_signoff_required": false,
    "topics": [

    ],
    "visibility": "public",
    "forks": 0,
    "open_issues": 0,
    "watchers": 0,
    "default_branch": "main",
    "permissions": {
      "admin": true,
      "maintain": true,
      "push": true,
      "triage": true,
      "pull": true
    }
  },
  {
    "id": 1132028291,
    "node_id": "R_kgDOQ3lhgw",
    "name": "Basketball_action_recoginition_sever",
    "full_name": "charlie2233/Basketball_action_recoginition_sever",
    "private": false,
    "owner": {
      "login": "charlie2233",
      "id": 117957000,
      "node_id": "U_kgDOBwfhiA",
      "avatar_url": "https://avatars.githubusercontent.com/u/117957000?v=4",
      "gravatar_id": "",
      "url": "https://api.github.com/users/charlie2233",
      "html_url": "https://github.com/charlie2233",
      "followers_url": "https://api.github.com/users/charlie2233/followers",
      "following_url": "https://api.github.com/users/charlie2233/following{/other_user}",
      "gists_url": "https://api.github.com/users/charlie2233/gists{/gist_id}",
      "starred_url": "https://api.github.com/users/charlie2233/starred{/owner}{/repo}",
      "subscriptions_url": "https://api.github.com/users/charlie2233/subscriptions",
      "organizations_url": "https://api.github.com/users/charlie2233/orgs",
      "repos_url": "https://api.github.com/users/charlie2233/repos",
      "events_url": "https://api.github.com/users/charlie2233/events{/privacy}",
      "received_events_url": "https://api.github.com/users/charlie2233/received_events",
      "type": "User",
      "user_view_type": "public",
      "site_admin": false
    },
    "html_url": "https://github.com/charlie2233/Basketball_action_recoginition_sever",
    "description": null,
    "fork": false,
    "url": "https://api.github.com/repos/charlie2233/Basketball_action_recoginition_sever",
    "forks_url": "https://api.github.com/repos/charlie2233/Basketball_action_recoginition_sever/forks",
    "keys_url": "https://api.github.com/repos/charlie2233/Basketball_action_recoginition_sever/keys{/key_id}",
    "collaborators_url": "https://api.github.com/repos/charlie2233/Basketball_action_recoginition_sever/collaborators{/collaborator}",
    "teams_url": "https://api.github.com/repos/charlie2233/Basketball_action_recoginition_sever/teams",
    "hooks_url": "https://api.github.com/repos/charlie2233/Basketball_action_recoginition_sever/hooks",
    "issue_events_url": "https://api.github.com/repos/charlie2233/Basketball_action_recoginition_sever/issues/events{/number}",
    "events_url": "https://api.github.com/repos/charlie2233/Basketball_action_recoginition_sever/events",
    "assignees_url": "https://api.github.com/repos/charlie2233/Basketball_action_recoginition_sever/assignees{/user}",
    "branches_url": "https://api.github.com/repos/charlie2233/Basketball_action_recoginition_sever/branches{/branch}",
    "tags_url": "https://api.github.com/repos/charlie2233/Basketball_action_recoginition_sever/tags",
    "blobs_url": "https://api.github.com/repos/charlie2233/Basketball_action_recoginition_sever/git/blobs{/sha}",
    "git_tags_url": "https://api.github.com/repos/charlie2233/Basketball_action_recoginition_sever/git/tags{/sha}",
    "git_refs_url": "https://api.github.com/repos/charlie2233/Basketball_action_recoginition_sever/git/refs{/sha}",
    "trees_url": "https://api.github.com/repos/charlie2233/Basketball_action_recoginition_sever/git/trees{/sha}",
    "statuses_url": "https://api.github.com/repos/charlie2233/Basketball_action_recoginition_sever/statuses/{sha}",
    "languages_url": "https://api.github.com/repos/charlie2233/Basketball_action_recoginition_sever/languages",
    "stargazers_url": "https://api.github.com/repos/charlie2233/Basketball_action_recoginition_sever/stargazers",
    "contributors_url": "https://api.github.com/repos/charlie2233/Basketball_action_recoginition_sever/contributors",
    "subscribers_url": "https://api.github.com/repos/charlie2233/Basketball_action_recoginition_sever/subscribers",
    "subscription_url": "https://api.github.com/repos/charlie2233/Basketball_action_recoginition_sever/subscription",
    "commits_url": "https://api.github.com/repos/charlie2233/Basketball_action_recoginition_sever/commits{/sha}",
    "git_commits_url": "https://api.github.com/repos/charlie2233/Basketball_action_recoginition_sever/git/commits{/sha}",
    "comments_url": "https://api.github.com/repos/charlie2233/Basketball_action_recoginition_sever/comments{/number}",
    "issue_comment_url": "https://api.github.com/repos/charlie2233/Basketball_action_recoginition_sever/issues/comments{/number}",
    "contents_url": "https://api.github.com/repos/charlie2233/Basketball_action_recoginition_sever/contents/{+path}",
    "compare_url": "https://api.github.com/repos/charlie2233/Basketball_action_recoginition_sever/compare/{base}...{head}",
    "merges_url": "https://api.github.com/repos/charlie2233/Basketball_action_recoginition_sever/merges",
    "archive_url": "https://api.github.com/repos/charlie2233/Basketball_action_recoginition_sever/{archive_format}{/ref}",
    "downloads_url": "https://api.github.com/repos/charlie2233/Basketball_action_recoginition_sever/downloads",
    "issues_url": "https://api.github.com/repos/charlie2233/Basketball_action_recoginition_sever/issues{/number}",
    "pulls_url": "https://api.github.com/repos/charlie2233/Basketball_action_recoginition_sever/pulls{/number}",
    "milestones_url": "https://api.github.com/repos/charlie2233/Basketball_action_recoginition_sever/milestones{/number}",
    "notifications_url": "https://api.github.com/repos/charlie2233/Basketball_action_recoginition_sever/notifications{?since,all,participating}",
    "labels_url": "https://api.github.com/repos/charlie2233/Basketball_action_recoginition_sever/labels{/name}",
    "releases_url": "https://api.github.com/repos/charlie2233/Basketball_action_recoginition_sever/releases{/id}",
    "deployments_url": "https://api.github.com/repos/charlie2233/Basketball_action_recoginition_sever/deployments",
    "created_at": "2026-01-11T07:01:29Z",
    "updated_at": "2026-01-11T07:09:13Z",
    "pushed_at": "2026-01-11T07:09:03Z",
    "git_url": "git://github.com/charlie2233/Basketball_action_recoginition_sever.git",
    "ssh_url": "git@github.com:charlie2233/Basketball_action_recoginition_sever.git",
    "clone_url": "https://github.com/charlie2233/Basketball_action_recoginition_sever.git",
    "svn_url": "https://github.com/charlie2233/Basketball_action_recoginition_sever",
    "homepage": null,
    "size": 91875,
    "stargazers_count": 0,
    "watchers_count": 0,
    "language": "Jupyter Notebook",
    "has_issues": true,
    "has_projects": true,
    "has_downloads": true,
    "has_wiki": true,
    "has_pages": false,
    "has_discussions": false,
    "forks_count": 0,
    "mirror_url": null,
    "archived": false,
    "disabled": false,
    "open_issues_count": 0,
    "license": {
      "key": "mit",
      "name": "MIT License",
      "spdx_id": "MIT",
      "url": "https://api.github.com/licenses/mit",
      "node_id": "MDc6TGljZW5zZTEz"
    },
    "allow_forking": true,
    "is_template": false,
    "web_commit_signoff_required": false,
    "topics": [

    ],
    "visibility": "public",
    "forks": 0,
    "open_issues": 0,
    "watchers": 0,
    "default_branch": "main",
    "permissions": {
      "admin": true,
      "maintain": true,
      "push": true,
      "triage": true,
      "pull": true
    }
  },
  {
    "id": 1131314134,
    "node_id": "R_kgDOQ2571g",
    "name": "AI-predator-simulation",
    "full_name": "charlie2233/AI-predator-simulation",
    "private": false,
    "owner": {
      "login": "charlie2233",
      "id": 117957000,
      "node_id": "U_kgDOBwfhiA",
      "avatar_url": "https://avatars.githubusercontent.com/u/117957000?v=4",
      "gravatar_id": "",
      "url": "https://api.github.com/users/charlie2233",
      "html_url": "https://github.com/charlie2233",
      "followers_url": "https://api.github.com/users/charlie2233/followers",
      "following_url": "https://api.github.com/users/charlie2233/following{/other_user}",
      "gists_url": "https://api.github.com/users/charlie2233/gists{/gist_id}",
      "starred_url": "https://api.github.com/users/charlie2233/starred{/owner}{/repo}",
      "subscriptions_url": "https://api.github.com/users/charlie2233/subscriptions",
      "organizations_url": "https://api.github.com/users/charlie2233/orgs",
      "repos_url": "https://api.github.com/users/charlie2233/repos",
      "events_url": "https://api.github.com/users/charlie2233/events{/privacy}",
      "received_events_url": "https://api.github.com/users/charlie2233/received_events",
      "type": "User",
      "user_view_type": "public",
      "site_admin": false
    },
    "html_url": "https://github.com/charlie2233/AI-predator-simulation",
    "description": null,
    "fork": false,
    "url": "https://api.github.com/repos/charlie2233/AI-predator-simulation",
    "forks_url": "https://api.github.com/repos/charlie2233/AI-predator-simulation/forks",
    "keys_url": "https://api.github.com/repos/charlie2233/AI-predator-simulation/keys{/key_id}",
    "collaborators_url": "https://api.github.com/repos/charlie2233/AI-predator-simulation/collaborators{/collaborator}",
    "teams_url": "https://api.github.com/repos/charlie2233/AI-predator-simulation/teams",
    "hooks_url": "https://api.github.com/repos/charlie2233/AI-predator-simulation/hooks",
    "issue_events_url": "https://api.github.com/repos/charlie2233/AI-predator-simulation/issues/events{/number}",
    "events_url": "https://api.github.com/repos/charlie2233/AI-predator-simulation/events",
    "assignees_url": "https://api.github.com/repos/charlie2233/AI-predator-simulation/assignees{/user}",
    "branches_url": "https://api.github.com/repos/charlie2233/AI-predator-simulation/branches{/branch}",
    "tags_url": "https://api.github.com/repos/charlie2233/AI-predator-simulation/tags",
    "blobs_url": "https://api.github.com/repos/charlie2233/AI-predator-simulation/git/blobs{/sha}",
    "git_tags_url": "https://api.github.com/repos/charlie2233/AI-predator-simulation/git/tags{/sha}",
    "git_refs_url": "https://api.github.com/repos/charlie2233/AI-predator-simulation/git/refs{/sha}",
    "trees_url": "https://api.github.com/repos/charlie2233/AI-predator-simulation/git/trees{/sha}",
    "statuses_url": "https://api.github.com/repos/charlie2233/AI-predator-simulation/statuses/{sha}",
    "languages_url": "https://api.github.com/repos/charlie2233/AI-predator-simulation/languages",
    "stargazers_url": "https://api.github.com/repos/charlie2233/AI-predator-simulation/stargazers",
    "contributors_url": "https://api.github.com/repos/charlie2233/AI-predator-simulation/contributors",
    "subscribers_url": "https://api.github.com/repos/charlie2233/AI-predator-simulation/subscribers",
    "subscription_url": "https://api.github.com/repos/charlie2233/AI-predator-simulation/subscription",
    "commits_url": "https://api.github.com/repos/charlie2233/AI-predator-simulation/commits{/sha}",
    "git_commits_url": "https://api.github.com/repos/charlie2233/AI-predator-simulation/git/commits{/sha}",
    "comments_url": "https://api.github.com/repos/charlie2233/AI-predator-simulation/comments{/number}",
    "issue_comment_url": "https://api.github.com/repos/charlie2233/AI-predator-simulation/issues/comments{/number}",
    "contents_url": "https://api.github.com/repos/charlie2233/AI-predator-simulation/contents/{+path}",
    "compare_url": "https://api.github.com/repos/charlie2233/AI-predator-simulation/compare/{base}...{head}",
    "merges_url": "https://api.github.com/repos/charlie2233/AI-predator-simulation/merges",
    "archive_url": "https://api.github.com/repos/charlie2233/AI-predator-simulation/{archive_format}{/ref}",
    "downloads_url": "https://api.github.com/repos/charlie2233/AI-predator-simulation/downloads",
    "issues_url": "https://api.github.com/repos/charlie2233/AI-predator-simulation/issues{/number}",
    "pulls_url": "https://api.github.com/repos/charlie2233/AI-predator-simulation/pulls{/number}",
    "milestones_url": "https://api.github.com/repos/charlie2233/AI-predator-simulation/milestones{/number}",
    "notifications_url": "https://api.github.com/repos/charlie2233/AI-predator-simulation/notifications{?since,all,participating}",
    "labels_url": "https://api.github.com/repos/charlie2233/AI-predator-simulation/labels{/name}",
    "releases_url": "https://api.github.com/repos/charlie2233/AI-predator-simulation/releases{/id}",
    "deployments_url": "https://api.github.com/repos/charlie2233/AI-predator-simulation/deployments",
    "created_at": "2026-01-09T20:01:02Z",
    "updated_at": "2026-01-10T07:38:09Z",
    "pushed_at": "2026-01-10T07:38:05Z",
    "git_url": "git://github.com/charlie2233/AI-predator-simulation.git",
    "ssh_url": "git@github.com:charlie2233/AI-predator-simulation.git",
    "clone_url": "https://github.com/charlie2233/AI-predator-simulation.git",
    "svn_url": "https://github.com/charlie2233/AI-predator-simulation",
    "homepage": null,
    "size": 326,
    "stargazers_count": 0,
    "watchers_count": 0,
    "language": "Python",
    "has_issues": true,
    "has_projects": true,
    "has_downloads": true,
    "has_wiki": true,
    "has_pages": false,
    "has_discussions": false,
    "forks_count": 0,
    "mirror_url": null,
    "archived": false,
    "disabled": false,
    "open_issues_count": 0,
    "license": {
      "key": "mit",
      "name": "MIT License",
      "spdx_id": "MIT",
      "url": "https://api.github.com/licenses/mit",
      "node_id": "MDc6TGljZW5zZTEz"
    },
    "allow_forking": true,
    "is_template": false,
    "web_commit_signoff_required": false,
    "topics": [

    ],
    "visibility": "public",
    "forks": 0,
    "open_issues": 0,
    "watchers": 0,
    "default_branch": "main",
    "permissions": {
      "admin": true,
      "maintain": true,
      "push": true,
      "triage": true,
      "pull": true
    }
  },
  {
    "id": 1131525028,
    "node_id": "R_kgDOQ3GzpA",
    "name": "Easy_command_prompt",
    "full_name": "charlie2233/Easy_command_prompt",
    "private": false,
    "owner": {
      "login": "charlie2233",
      "id": 117957000,
      "node_id": "U_kgDOBwfhiA",
      "avatar_url": "https://avatars.githubusercontent.com/u/117957000?v=4",
      "gravatar_id": "",
      "url": "https://api.github.com/users/charlie2233",
      "html_url": "https://github.com/charlie2233",
      "followers_url": "https://api.github.com/users/charlie2233/followers",
      "following_url": "https://api.github.com/users/charlie2233/following{/other_user}",
      "gists_url": "https://api.github.com/users/charlie2233/gists{/gist_id}",
      "starred_url": "https://api.github.com/users/charlie2233/starred{/owner}{/repo}",
      "subscriptions_url": "https://api.github.com/users/charlie2233/subscriptions",
      "organizations_url": "https://api.github.com/users/charlie2233/orgs",
      "repos_url": "https://api.github.com/users/charlie2233/repos",
      "events_url": "https://api.github.com/users/charlie2233/events{/privacy}",
      "received_events_url": "https://api.github.com/users/charlie2233/received_events",
      "type": "User",
      "user_view_type": "public",
      "site_admin": false
    },
    "html_url": "https://github.com/charlie2233/Easy_command_prompt",
    "description": null,
    "fork": false,
    "url": "https://api.github.com/repos/charlie2233/Easy_command_prompt",
    "forks_url": "https://api.github.com/repos/charlie2233/Easy_command_prompt/forks",
    "keys_url": "https://api.github.com/repos/charlie2233/Easy_command_prompt/keys{/key_id}",
    "collaborators_url": "https://api.github.com/repos/charlie2233/Easy_command_prompt/collaborators{/collaborator}",
    "teams_url": "https://api.github.com/repos/charlie2233/Easy_command_prompt/teams",
    "hooks_url": "https://api.github.com/repos/charlie2233/Easy_command_prompt/hooks",
    "issue_events_url": "https://api.github.com/repos/charlie2233/Easy_command_prompt/issues/events{/number}",
    "events_url": "https://api.github.com/repos/charlie2233/Easy_command_prompt/events",
    "assignees_url": "https://api.github.com/repos/charlie2233/Easy_command_prompt/assignees{/user}",
    "branches_url": "https://api.github.com/repos/charlie2233/Easy_command_prompt/branches{/branch}",
    "tags_url": "https://api.github.com/repos/charlie2233/Easy_command_prompt/tags",
    "blobs_url": "https://api.github.com/repos/charlie2233/Easy_command_prompt/git/blobs{/sha}",
    "git_tags_url": "https://api.github.com/repos/charlie2233/Easy_command_prompt/git/tags{/sha}",
    "git_refs_url": "https://api.github.com/repos/charlie2233/Easy_command_prompt/git/refs{/sha}",
    "trees_url": "https://api.github.com/repos/charlie2233/Easy_command_prompt/git/trees{/sha}",
    "statuses_url": "https://api.github.com/repos/charlie2233/Easy_command_prompt/statuses/{sha}",
    "languages_url": "https://api.github.com/repos/charlie2233/Easy_command_prompt/languages",
    "stargazers_url": "https://api.github.com/repos/charlie2233/Easy_command_prompt/stargazers",
    "contributors_url": "https://api.github.com/repos/charlie2233/Easy_command_prompt/contributors",
    "subscribers_url": "https://api.github.com/repos/charlie2233/Easy_command_prompt/subscribers",
    "subscription_url": "https://api.github.com/repos/charlie2233/Easy_command_prompt/subscription",
    "commits_url": "https://api.github.com/repos/charlie2233/Easy_command_prompt/commits{/sha}",
    "git_commits_url": "https://api.github.com/repos/charlie2233/Easy_command_prompt/git/commits{/sha}",
    "comments_url": "https://api.github.com/repos/charlie2233/Easy_command_prompt/comments{/number}",
    "issue_comment_url": "https://api.github.com/repos/charlie2233/Easy_command_prompt/issues/comments{/number}",
    "contents_url": "https://api.github.com/repos/charlie2233/Easy_command_prompt/contents/{+path}",
    "compare_url": "https://api.github.com/repos/charlie2233/Easy_command_prompt/compare/{base}...{head}",
    "merges_url": "https://api.github.com/repos/charlie2233/Easy_command_prompt/merges",
    "archive_url": "https://api.github.com/repos/charlie2233/Easy_command_prompt/{archive_format}{/ref}",
    "downloads_url": "https://api.github.com/repos/charlie2233/Easy_command_prompt/downloads",
    "issues_url": "https://api.github.com/repos/charlie2233/Easy_command_prompt/issues{/number}",
    "pulls_url": "https://api.github.com/repos/charlie2233/Easy_command_prompt/pulls{/number}",
    "milestones_url": "https://api.github.com/repos/charlie2233/Easy_command_prompt/milestones{/number}",
    "notifications_url": "https://api.github.com/repos/charlie2233/Easy_command_prompt/notifications{?since,all,participating}",
    "labels_url": "https://api.github.com/repos/charlie2233/Easy_command_prompt/labels{/name}",
    "releases_url": "https://api.github.com/repos/charlie2233/Easy_command_prompt/releases{/id}",
    "deployments_url": "https://api.github.com/repos/charlie2233/Easy_command_prompt/deployments",
    "created_at": "2026-01-10T07:14:28Z",
    "updated_at": "2026-01-10T07:14:32Z",
    "pushed_at": "2026-01-10T07:14:28Z",
    "git_url": "git://github.com/charlie2233/Easy_command_prompt.git",
    "ssh_url": "git@github.com:charlie2233/Easy_command_prompt.git",
    "clone_url": "https://github.com/charlie2233/Easy_command_prompt.git",
    "svn_url": "https://github.com/charlie2233/Easy_command_prompt",
    "homepage": null,
    "size": 1,
    "stargazers_count": 0,
    "watchers_count": 0,
    "language": null,
    "has_issues": true,
    "has_projects": true,
    "has_downloads": true,
    "has_wiki": true,
    "has_pages": false,
    "has_discussions": false,
    "forks_count": 0,
    "mirror_url": null,
    "archived": false,
    "disabled": false,
    "open_issues_count": 0,
    "license": {
      "key": "mit",
      "name": "MIT License",
      "spdx_id": "MIT",
      "url": "https://api.github.com/licenses/mit",
      "node_id": "MDc6TGljZW5zZTEz"
    },
    "allow_forking": true,
    "is_template": false,
    "web_commit_signoff_required": false,
    "topics": [

    ],
    "visibility": "public",
    "forks": 0,
    "open_issues": 0,
    "watchers": 0,
    "default_branch": "main",
    "permissions": {
      "admin": true,
      "maintain": true,
      "push": true,
      "triage": true,
      "pull": true
    }
  },
  {
    "id": 1087341888,
    "node_id": "R_kgDOQM-FQA",
    "name": "MazeRunner67ers_APCSA_Java",
    "full_name": "charlie2233/MazeRunner67ers_APCSA_Java",
    "private": false,
    "owner": {
      "login": "charlie2233",
      "id": 117957000,
      "node_id": "U_kgDOBwfhiA",
      "avatar_url": "https://avatars.githubusercontent.com/u/117957000?v=4",
      "gravatar_id": "",
      "url": "https://api.github.com/users/charlie2233",
      "html_url": "https://github.com/charlie2233",
      "followers_url": "https://api.github.com/users/charlie2233/followers",
      "following_url": "https://api.github.com/users/charlie2233/following{/other_user}",
      "gists_url": "https://api.github.com/users/charlie2233/gists{/gist_id}",
      "starred_url": "https://api.github.com/users/charlie2233/starred{/owner}{/repo}",
      "subscriptions_url": "https://api.github.com/users/charlie2233/subscriptions",
      "organizations_url": "https://api.github.com/users/charlie2233/orgs",
      "repos_url": "https://api.github.com/users/charlie2233/repos",
      "events_url": "https://api.github.com/users/charlie2233/events{/privacy}",
      "received_events_url": "https://api.github.com/users/charlie2233/received_events",
      "type": "User",
      "user_view_type": "public",
      "site_admin": false
    },
    "html_url": "https://github.com/charlie2233/MazeRunner67ers_APCSA_Java",
    "description": null,
    "fork": false,
    "url": "https://api.github.com/repos/charlie2233/MazeRunner67ers_APCSA_Java",
    "forks_url": "https://api.github.com/repos/charlie2233/MazeRunner67ers_APCSA_Java/forks",
    "keys_url": "https://api.github.com/repos/charlie2233/MazeRunner67ers_APCSA_Java/keys{/key_id}",
    "collaborators_url": "https://api.github.com/repos/charlie2233/MazeRunner67ers_APCSA_Java/collaborators{/collaborator}",
    "teams_url": "https://api.github.com/repos/charlie2233/MazeRunner67ers_APCSA_Java/teams",
    "hooks_url": "https://api.github.com/repos/charlie2233/MazeRunner67ers_APCSA_Java/hooks",
    "issue_events_url": "https://api.github.com/repos/charlie2233/MazeRunner67ers_APCSA_Java/issues/events{/number}",
    "events_url": "https://api.github.com/repos/charlie2233/MazeRunner67ers_APCSA_Java/events",
    "assignees_url": "https://api.github.com/repos/charlie2233/MazeRunner67ers_APCSA_Java/assignees{/user}",
    "branches_url": "https://api.github.com/repos/charlie2233/MazeRunner67ers_APCSA_Java/branches{/branch}",
    "tags_url": "https://api.github.com/repos/charlie2233/MazeRunner67ers_APCSA_Java/tags",
    "blobs_url": "https://api.github.com/repos/charlie2233/MazeRunner67ers_APCSA_Java/git/blobs{/sha}",
    "git_tags_url": "https://api.github.com/repos/charlie2233/MazeRunner67ers_APCSA_Java/git/tags{/sha}",
    "git_refs_url": "https://api.github.com/repos/charlie2233/MazeRunner67ers_APCSA_Java/git/refs{/sha}",
    "trees_url": "https://api.github.com/repos/charlie2233/MazeRunner67ers_APCSA_Java/git/trees{/sha}",
    "statuses_url": "https://api.github.com/repos/charlie2233/MazeRunner67ers_APCSA_Java/statuses/{sha}",
    "languages_url": "https://api.github.com/repos/charlie2233/MazeRunner67ers_APCSA_Java/languages",
    "stargazers_url": "https://api.github.com/repos/charlie2233/MazeRunner67ers_APCSA_Java/stargazers",
    "contributors_url": "https://api.github.com/repos/charlie2233/MazeRunner67ers_APCSA_Java/contributors",
    "subscribers_url": "https://api.github.com/repos/charlie2233/MazeRunner67ers_APCSA_Java/subscribers",
    "subscription_url": "https://api.github.com/repos/charlie2233/MazeRunner67ers_APCSA_Java/subscription",
    "commits_url": "https://api.github.com/repos/charlie2233/MazeRunner67ers_APCSA_Java/commits{/sha}",
    "git_commits_url": "https://api.github.com/repos/charlie2233/MazeRunner67ers_APCSA_Java/git/commits{/sha}",
    "comments_url": "https://api.github.com/repos/charlie2233/MazeRunner67ers_APCSA_Java/comments{/number}",
    "issue_comment_url": "https://api.github.com/repos/charlie2233/MazeRunner67ers_APCSA_Java/issues/comments{/number}",
    "contents_url": "https://api.github.com/repos/charlie2233/MazeRunner67ers_APCSA_Java/contents/{+path}",
    "compare_url": "https://api.github.com/repos/charlie2233/MazeRunner67ers_APCSA_Java/compare/{base}...{head}",
    "merges_url": "https://api.github.com/repos/charlie2233/MazeRunner67ers_APCSA_Java/merges",
    "archive_url": "https://api.github.com/repos/charlie2233/MazeRunner67ers_APCSA_Java/{archive_format}{/ref}",
    "downloads_url": "https://api.github.com/repos/charlie2233/MazeRunner67ers_APCSA_Java/downloads",
    "issues_url": "https://api.github.com/repos/charlie2233/MazeRunner67ers_APCSA_Java/issues{/number}",
    "pulls_url": "https://api.github.com/repos/charlie2233/MazeRunner67ers_APCSA_Java/pulls{/number}",
    "milestones_url": "https://api.github.com/repos/charlie2233/MazeRunner67ers_APCSA_Java/milestones{/number}",
    "notifications_url": "https://api.github.com/repos/charlie2233/MazeRunner67ers_APCSA_Java/notifications{?since,all,participating}",
    "labels_url": "https://api.github.com/repos/charlie2233/MazeRunner67ers_APCSA_Java/labels{/name}",
    "releases_url": "https://api.github.com/repos/charlie2233/MazeRunner67ers_APCSA_Java/releases{/id}",
    "deployments_url": "https://api.github.com/repos/charlie2233/MazeRunner67ers_APCSA_Java/deployments",
    "created_at": "2025-10-31T18:44:16Z",
    "updated_at": "2025-12-20T07:06:06Z",
    "pushed_at": "2025-12-20T07:06:02Z",
    "git_url": "git://github.com/charlie2233/MazeRunner67ers_APCSA_Java.git",
    "ssh_url": "git@github.com:charlie2233/MazeRunner67ers_APCSA_Java.git",
    "clone_url": "https://github.com/charlie2233/MazeRunner67ers_APCSA_Java.git",
    "svn_url": "https://github.com/charlie2233/MazeRunner67ers_APCSA_Java",
    "homepage": null,
    "size": 3125,
    "stargazers_count": 0,
    "watchers_count": 0,
    "language": "Java",
    "has_issues": true,
    "has_projects": true,
    "has_downloads": true,
    "has_wiki": true,
    "has_pages": false,
    "has_discussions": false,
    "forks_count": 0,
    "mirror_url": null,
    "archived": false,
    "disabled": false,
    "open_issues_count": 0,
    "license": {
      "key": "mit",
      "name": "MIT License",
      "spdx_id": "MIT",
      "url": "https://api.github.com/licenses/mit",
      "node_id": "MDc6TGljZW5zZTEz"
    },
    "allow_forking": true,
    "is_template": false,
    "web_commit_signoff_required": false,
    "topics": [

    ],
    "visibility": "public",
    "forks": 0,
    "open_issues": 0,
    "watchers": 0,
    "default_branch": "main",
    "permissions": {
      "admin": true,
      "maintain": true,
      "push": true,
      "triage": true,
      "pull": true
    }
  },
  {
    "id": 1110246237,
    "node_id": "R_kgDOQi0DXQ",
    "name": "CredibleSource_Investigator",
    "full_name": "charlie2233/CredibleSource_Investigator",
    "private": false,
    "owner": {
      "login": "charlie2233",
      "id": 117957000,
      "node_id": "U_kgDOBwfhiA",
      "avatar_url": "https://avatars.githubusercontent.com/u/117957000?v=4",
      "gravatar_id": "",
      "url": "https://api.github.com/users/charlie2233",
      "html_url": "https://github.com/charlie2233",
      "followers_url": "https://api.github.com/users/charlie2233/followers",
      "following_url": "https://api.github.com/users/charlie2233/following{/other_user}",
      "gists_url": "https://api.github.com/users/charlie2233/gists{/gist_id}",
      "starred_url": "https://api.github.com/users/charlie2233/starred{/owner}{/repo}",
      "subscriptions_url": "https://api.github.com/users/charlie2233/subscriptions",
      "organizations_url": "https://api.github.com/users/charlie2233/orgs",
      "repos_url": "https://api.github.com/users/charlie2233/repos",
      "events_url": "https://api.github.com/users/charlie2233/events{/privacy}",
      "received_events_url": "https://api.github.com/users/charlie2233/received_events",
      "type": "User",
      "user_view_type": "public",
      "site_admin": false
    },
    "html_url": "https://github.com/charlie2233/CredibleSource_Investigator",
    "description": "is ts a credible source asked by ur English teacher",
    "fork": false,
    "url": "https://api.github.com/repos/charlie2233/CredibleSource_Investigator",
    "forks_url": "https://api.github.com/repos/charlie2233/CredibleSource_Investigator/forks",
    "keys_url": "https://api.github.com/repos/charlie2233/CredibleSource_Investigator/keys{/key_id}",
    "collaborators_url": "https://api.github.com/repos/charlie2233/CredibleSource_Investigator/collaborators{/collaborator}",
    "teams_url": "https://api.github.com/repos/charlie2233/CredibleSource_Investigator/teams",
    "hooks_url": "https://api.github.com/repos/charlie2233/CredibleSource_Investigator/hooks",
    "issue_events_url": "https://api.github.com/repos/charlie2233/CredibleSource_Investigator/issues/events{/number}",
    "events_url": "https://api.github.com/repos/charlie2233/CredibleSource_Investigator/events",
    "assignees_url": "https://api.github.com/repos/charlie2233/CredibleSource_Investigator/assignees{/user}",
    "branches_url": "https://api.github.com/repos/charlie2233/CredibleSource_Investigator/branches{/branch}",
    "tags_url": "https://api.github.com/repos/charlie2233/CredibleSource_Investigator/tags",
    "blobs_url": "https://api.github.com/repos/charlie2233/CredibleSource_Investigator/git/blobs{/sha}",
    "git_tags_url": "https://api.github.com/repos/charlie2233/CredibleSource_Investigator/git/tags{/sha}",
    "git_refs_url": "https://api.github.com/repos/charlie2233/CredibleSource_Investigator/git/refs{/sha}",
    "trees_url": "https://api.github.com/repos/charlie2233/CredibleSource_Investigator/git/trees{/sha}",
    "statuses_url": "https://api.github.com/repos/charlie2233/CredibleSource_Investigator/statuses/{sha}",
    "languages_url": "https://api.github.com/repos/charlie2233/CredibleSource_Investigator/languages",
    "stargazers_url": "https://api.github.com/repos/charlie2233/CredibleSource_Investigator/stargazers",
    "contributors_url": "https://api.github.com/repos/charlie2233/CredibleSource_Investigator/contributors",
    "subscribers_url": "https://api.github.com/repos/charlie2233/CredibleSource_Investigator/subscribers",
    "subscription_url": "https://api.github.com/repos/charlie2233/CredibleSource_Investigator/subscription",
    "commits_url": "https://api.github.com/repos/charlie2233/CredibleSource_Investigator/commits{/sha}",
    "git_commits_url": "https://api.github.com/repos/charlie2233/CredibleSource_Investigator/git/commits{/sha}",
    "comments_url": "https://api.github.com/repos/charlie2233/CredibleSource_Investigator/comments{/number}",
    "issue_comment_url": "https://api.github.com/repos/charlie2233/CredibleSource_Investigator/issues/comments{/number}",
    "contents_url": "https://api.github.com/repos/charlie2233/CredibleSource_Investigator/contents/{+path}",
    "compare_url": "https://api.github.com/repos/charlie2233/CredibleSource_Investigator/compare/{base}...{head}",
    "merges_url": "https://api.github.com/repos/charlie2233/CredibleSource_Investigator/merges",
    "archive_url": "https://api.github.com/repos/charlie2233/CredibleSource_Investigator/{archive_format}{/ref}",
    "downloads_url": "https://api.github.com/repos/charlie2233/CredibleSource_Investigator/downloads",
    "issues_url": "https://api.github.com/repos/charlie2233/CredibleSource_Investigator/issues{/number}",
    "pulls_url": "https://api.github.com/repos/charlie2233/CredibleSource_Investigator/pulls{/number}",
    "milestones_url": "https://api.github.com/repos/charlie2233/CredibleSource_Investigator/milestones{/number}",
    "notifications_url": "https://api.github.com/repos/charlie2233/CredibleSource_Investigator/notifications{?since,all,participating}",
    "labels_url": "https://api.github.com/repos/charlie2233/CredibleSource_Investigator/labels{/name}",
    "releases_url": "https://api.github.com/repos/charlie2233/CredibleSource_Investigator/releases{/id}",
    "deployments_url": "https://api.github.com/repos/charlie2233/CredibleSource_Investigator/deployments",
    "created_at": "2025-12-04T23:15:06Z",
    "updated_at": "2025-12-04T23:23:06Z",
    "pushed_at": "2025-12-04T23:23:02Z",
    "git_url": "git://github.com/charlie2233/CredibleSource_Investigator.git",
    "ssh_url": "git@github.com:charlie2233/CredibleSource_Investigator.git",
    "clone_url": "https://github.com/charlie2233/CredibleSource_Investigator.git",
    "svn_url": "https://github.com/charlie2233/CredibleSource_Investigator",
    "homepage": null,
    "size": 18,
    "stargazers_count": 0,
    "watchers_count": 0,
    "language": "Python",
    "has_issues": true,
    "has_projects": true,
    "has_downloads": true,
    "has_wiki": true,
    "has_pages": false,
    "has_discussions": false,
    "forks_count": 0,
    "mirror_url": null,
    "archived": false,
    "disabled": false,
    "open_issues_count": 0,
    "license": {
      "key": "gpl-3.0",
      "name": "GNU General Public License v3.0",
      "spdx_id": "GPL-3.0",
      "url": "https://api.github.com/licenses/gpl-3.0",
      "node_id": "MDc6TGljZW5zZTk="
    },
    "allow_forking": true,
    "is_template": false,
    "web_commit_signoff_required": false,
    "topics": [

    ],
    "visibility": "public",
    "forks": 0,
    "open_issues": 0,
    "watchers": 0,
    "default_branch": "main",
    "permissions": {
      "admin": true,
      "maintain": true,
      "push": true,
      "triage": true,
      "pull": true
    }
  },
  {
    "id": 1106813366,
    "node_id": "R_kgDOQfihtg",
    "name": "screenLocks_detectsFaceGuard",
    "full_name": "charlie2233/screenLocks_detectsFaceGuard",
    "private": false,
    "owner": {
      "login": "charlie2233",
      "id": 117957000,
      "node_id": "U_kgDOBwfhiA",
      "avatar_url": "https://avatars.githubusercontent.com/u/117957000?v=4",
      "gravatar_id": "",
      "url": "https://api.github.com/users/charlie2233",
      "html_url": "https://github.com/charlie2233",
      "followers_url": "https://api.github.com/users/charlie2233/followers",
      "following_url": "https://api.github.com/users/charlie2233/following{/other_user}",
      "gists_url": "https://api.github.com/users/charlie2233/gists{/gist_id}",
      "starred_url": "https://api.github.com/users/charlie2233/starred{/owner}{/repo}",
      "subscriptions_url": "https://api.github.com/users/charlie2233/subscriptions",
      "organizations_url": "https://api.github.com/users/charlie2233/orgs",
      "repos_url": "https://api.github.com/users/charlie2233/repos",
      "events_url": "https://api.github.com/users/charlie2233/events{/privacy}",
      "received_events_url": "https://api.github.com/users/charlie2233/received_events",
      "type": "User",
      "user_view_type": "public",
      "site_admin": false
    },
    "html_url": "https://github.com/charlie2233/screenLocks_detectsFaceGuard",
    "description": "screenLocks_detectsFaceGuard",
    "fork": false,
    "url": "https://api.github.com/repos/charlie2233/screenLocks_detectsFaceGuard",
    "forks_url": "https://api.github.com/repos/charlie2233/screenLocks_detectsFaceGuard/forks",
    "keys_url": "https://api.github.com/repos/charlie2233/screenLocks_detectsFaceGuard/keys{/key_id}",
    "collaborators_url": "https://api.github.com/repos/charlie2233/screenLocks_detectsFaceGuard/collaborators{/collaborator}",
    "teams_url": "https://api.github.com/repos/charlie2233/screenLocks_detectsFaceGuard/teams",
    "hooks_url": "https://api.github.com/repos/charlie2233/screenLocks_detectsFaceGuard/hooks",
    "issue_events_url": "https://api.github.com/repos/charlie2233/screenLocks_detectsFaceGuard/issues/events{/number}",
    "events_url": "https://api.github.com/repos/charlie2233/screenLocks_detectsFaceGuard/events",
    "assignees_url": "https://api.github.com/repos/charlie2233/screenLocks_detectsFaceGuard/assignees{/user}",
    "branches_url": "https://api.github.com/repos/charlie2233/screenLocks_detectsFaceGuard/branches{/branch}",
    "tags_url": "https://api.github.com/repos/charlie2233/screenLocks_detectsFaceGuard/tags",
    "blobs_url": "https://api.github.com/repos/charlie2233/screenLocks_detectsFaceGuard/git/blobs{/sha}",
    "git_tags_url": "https://api.github.com/repos/charlie2233/screenLocks_detectsFaceGuard/git/tags{/sha}",
    "git_refs_url": "https://api.github.com/repos/charlie2233/screenLocks_detectsFaceGuard/git/refs{/sha}",
    "trees_url": "https://api.github.com/repos/charlie2233/screenLocks_detectsFaceGuard/git/trees{/sha}",
    "statuses_url": "https://api.github.com/repos/charlie2233/screenLocks_detectsFaceGuard/statuses/{sha}",
    "languages_url": "https://api.github.com/repos/charlie2233/screenLocks_detectsFaceGuard/languages",
    "stargazers_url": "https://api.github.com/repos/charlie2233/screenLocks_detectsFaceGuard/stargazers",
    "contributors_url": "https://api.github.com/repos/charlie2233/screenLocks_detectsFaceGuard/contributors",
    "subscribers_url": "https://api.github.com/repos/charlie2233/screenLocks_detectsFaceGuard/subscribers",
    "subscription_url": "https://api.github.com/repos/charlie2233/screenLocks_detectsFaceGuard/subscription",
    "commits_url": "https://api.github.com/repos/charlie2233/screenLocks_detectsFaceGuard/commits{/sha}",
    "git_commits_url": "https://api.github.com/repos/charlie2233/screenLocks_detectsFaceGuard/git/commits{/sha}",
    "comments_url": "https://api.github.com/repos/charlie2233/screenLocks_detectsFaceGuard/comments{/number}",
    "issue_comment_url": "https://api.github.com/repos/charlie2233/screenLocks_detectsFaceGuard/issues/comments{/number}",
    "contents_url": "https://api.github.com/repos/charlie2233/screenLocks_detectsFaceGuard/contents/{+path}",
    "compare_url": "https://api.github.com/repos/charlie2233/screenLocks_detectsFaceGuard/compare/{base}...{head}",
    "merges_url": "https://api.github.com/repos/charlie2233/screenLocks_detectsFaceGuard/merges",
    "archive_url": "https://api.github.com/repos/charlie2233/screenLocks_detectsFaceGuard/{archive_format}{/ref}",
    "downloads_url": "https://api.github.com/repos/charlie2233/screenLocks_detectsFaceGuard/downloads",
    "issues_url": "https://api.github.com/repos/charlie2233/screenLocks_detectsFaceGuard/issues{/number}",
    "pulls_url": "https://api.github.com/repos/charlie2233/screenLocks_detectsFaceGuard/pulls{/number}",
    "milestones_url": "https://api.github.com/repos/charlie2233/screenLocks_detectsFaceGuard/milestones{/number}",
    "notifications_url": "https://api.github.com/repos/charlie2233/screenLocks_detectsFaceGuard/notifications{?since,all,participating}",
    "labels_url": "https://api.github.com/repos/charlie2233/screenLocks_detectsFaceGuard/labels{/name}",
    "releases_url": "https://api.github.com/repos/charlie2233/screenLocks_detectsFaceGuard/releases{/id}",
    "deployments_url": "https://api.github.com/repos/charlie2233/screenLocks_detectsFaceGuard/deployments",
    "created_at": "2025-11-30T01:45:40Z",
    "updated_at": "2025-11-30T01:46:22Z",
    "pushed_at": "2025-11-30T01:46:18Z",
    "git_url": "git://github.com/charlie2233/screenLocks_detectsFaceGuard.git",
    "ssh_url": "git@github.com:charlie2233/screenLocks_detectsFaceGuard.git",
    "clone_url": "https://github.com/charlie2233/screenLocks_detectsFaceGuard.git",
    "svn_url": "https://github.com/charlie2233/screenLocks_detectsFaceGuard",
    "homepage": null,
    "size": 111,
    "stargazers_count": 0,
    "watchers_count": 0,
    "language": "Python",
    "has_issues": true,
    "has_projects": true,
    "has_downloads": true,
    "has_wiki": true,
    "has_pages": false,
    "has_discussions": false,
    "forks_count": 0,
    "mirror_url": null,
    "archived": false,
    "disabled": false,
    "open_issues_count": 0,
    "license": {
      "key": "mit",
      "name": "MIT License",
      "spdx_id": "MIT",
      "url": "https://api.github.com/licenses/mit",
      "node_id": "MDc6TGljZW5zZTEz"
    },
    "allow_forking": true,
    "is_template": false,
    "web_commit_signoff_required": false,
    "topics": [

    ],
    "visibility": "public",
    "forks": 0,
    "open_issues": 0,
    "watchers": 0,
    "default_branch": "main",
    "permissions": {
      "admin": true,
      "maintain": true,
      "push": true,
      "triage": true,
      "pull": true
    }
  },
  {
    "id": 1017643387,
    "node_id": "R_kgDOPKgBew",
    "name": "Thumbs-project",
    "full_name": "charlie2233/Thumbs-project",
    "private": false,
    "owner": {
      "login": "charlie2233",
      "id": 117957000,
      "node_id": "U_kgDOBwfhiA",
      "avatar_url": "https://avatars.githubusercontent.com/u/117957000?v=4",
      "gravatar_id": "",
      "url": "https://api.github.com/users/charlie2233",
      "html_url": "https://github.com/charlie2233",
      "followers_url": "https://api.github.com/users/charlie2233/followers",
      "following_url": "https://api.github.com/users/charlie2233/following{/other_user}",
      "gists_url": "https://api.github.com/users/charlie2233/gists{/gist_id}",
      "starred_url": "https://api.github.com/users/charlie2233/starred{/owner}{/repo}",
      "subscriptions_url": "https://api.github.com/users/charlie2233/subscriptions",
      "organizations_url": "https://api.github.com/users/charlie2233/orgs",
      "repos_url": "https://api.github.com/users/charlie2233/repos",
      "events_url": "https://api.github.com/users/charlie2233/events{/privacy}",
      "received_events_url": "https://api.github.com/users/charlie2233/received_events",
      "type": "User",
      "user_view_type": "public",
      "site_admin": false
    },
    "html_url": "https://github.com/charlie2233/Thumbs-project",
    "description": null,
    "fork": false,
    "url": "https://api.github.com/repos/charlie2233/Thumbs-project",
    "forks_url": "https://api.github.com/repos/charlie2233/Thumbs-project/forks",
    "keys_url": "https://api.github.com/repos/charlie2233/Thumbs-project/keys{/key_id}",
    "collaborators_url": "https://api.github.com/repos/charlie2233/Thumbs-project/collaborators{/collaborator}",
    "teams_url": "https://api.github.com/repos/charlie2233/Thumbs-project/teams",
    "hooks_url": "https://api.github.com/repos/charlie2233/Thumbs-project/hooks",
    "issue_events_url": "https://api.github.com/repos/charlie2233/Thumbs-project/issues/events{/number}",
    "events_url": "https://api.github.com/repos/charlie2233/Thumbs-project/events",
    "assignees_url": "https://api.github.com/repos/charlie2233/Thumbs-project/assignees{/user}",
    "branches_url": "https://api.github.com/repos/charlie2233/Thumbs-project/branches{/branch}",
    "tags_url": "https://api.github.com/repos/charlie2233/Thumbs-project/tags",
    "blobs_url": "https://api.github.com/repos/charlie2233/Thumbs-project/git/blobs{/sha}",
    "git_tags_url": "https://api.github.com/repos/charlie2233/Thumbs-project/git/tags{/sha}",
    "git_refs_url": "https://api.github.com/repos/charlie2233/Thumbs-project/git/refs{/sha}",
    "trees_url": "https://api.github.com/repos/charlie2233/Thumbs-project/git/trees{/sha}",
    "statuses_url": "https://api.github.com/repos/charlie2233/Thumbs-project/statuses/{sha}",
    "languages_url": "https://api.github.com/repos/charlie2233/Thumbs-project/languages",
    "stargazers_url": "https://api.github.com/repos/charlie2233/Thumbs-project/stargazers",
    "contributors_url": "https://api.github.com/repos/charlie2233/Thumbs-project/contributors",
    "subscribers_url": "https://api.github.com/repos/charlie2233/Thumbs-project/subscribers",
    "subscription_url": "https://api.github.com/repos/charlie2233/Thumbs-project/subscription",
    "commits_url": "https://api.github.com/repos/charlie2233/Thumbs-project/commits{/sha}",
    "git_commits_url": "https://api.github.com/repos/charlie2233/Thumbs-project/git/commits{/sha}",
    "comments_url": "https://api.github.com/repos/charlie2233/Thumbs-project/comments{/number}",
    "issue_comment_url": "https://api.github.com/repos/charlie2233/Thumbs-project/issues/comments{/number}",
    "contents_url": "https://api.github.com/repos/charlie2233/Thumbs-project/contents/{+path}",
    "compare_url": "https://api.github.com/repos/charlie2233/Thumbs-project/compare/{base}...{head}",
    "merges_url": "https://api.github.com/repos/charlie2233/Thumbs-project/merges",
    "archive_url": "https://api.github.com/repos/charlie2233/Thumbs-project/{archive_format}{/ref}",
    "downloads_url": "https://api.github.com/repos/charlie2233/Thumbs-project/downloads",
    "issues_url": "https://api.github.com/repos/charlie2233/Thumbs-project/issues{/number}",
    "pulls_url": "https://api.github.com/repos/charlie2233/Thumbs-project/pulls{/number}",
    "milestones_url": "https://api.github.com/repos/charlie2233/Thumbs-project/milestones{/number}",
    "notifications_url": "https://api.github.com/repos/charlie2233/Thumbs-project/notifications{?since,all,participating}",
    "labels_url": "https://api.github.com/repos/charlie2233/Thumbs-project/labels{/name}",
    "releases_url": "https://api.github.com/repos/charlie2233/Thumbs-project/releases{/id}",
    "deployments_url": "https://api.github.com/repos/charlie2233/Thumbs-project/deployments",
    "created_at": "2025-07-10T21:33:40Z",
    "updated_at": "2025-07-14T21:05:46Z",
    "pushed_at": "2025-07-14T21:05:42Z",
    "git_url": "git://github.com/charlie2233/Thumbs-project.git",
    "ssh_url": "git@github.com:charlie2233/Thumbs-project.git",
    "clone_url": "https://github.com/charlie2233/Thumbs-project.git",
    "svn_url": "https://github.com/charlie2233/Thumbs-project",
    "homepage": null,
    "size": 7,
    "stargazers_count": 0,
    "watchers_count": 0,
    "language": "Jupyter Notebook",
    "has_issues": true,
    "has_projects": true,
    "has_downloads": true,
    "has_wiki": true,
    "has_pages": false,
    "has_discussions": false,
    "forks_count": 0,
    "mirror_url": null,
    "archived": false,
    "disabled": false,
    "open_issues_count": 0,
    "license": null,
    "allow_forking": true,
    "is_template": false,
    "web_commit_signoff_required": false,
    "topics": [

    ],
    "visibility": "public",
    "forks": 0,
    "open_issues": 0,
    "watchers": 0,
    "default_branch": "main",
    "permissions": {
      "admin": true,
      "maintain": true,
      "push": true,
      "triage": true,
      "pull": true
    }
  },
  {
    "id": 945740379,
    "node_id": "R_kgDOOF7aWw",
    "name": "newproyecto",
    "full_name": "charlie2233/newproyecto",
    "private": false,
    "owner": {
      "login": "charlie2233",
      "id": 117957000,
      "node_id": "U_kgDOBwfhiA",
      "avatar_url": "https://avatars.githubusercontent.com/u/117957000?v=4",
      "gravatar_id": "",
      "url": "https://api.github.com/users/charlie2233",
      "html_url": "https://github.com/charlie2233",
      "followers_url": "https://api.github.com/users/charlie2233/followers",
      "following_url": "https://api.github.com/users/charlie2233/following{/other_user}",
      "gists_url": "https://api.github.com/users/charlie2233/gists{/gist_id}",
      "starred_url": "https://api.github.com/users/charlie2233/starred{/owner}{/repo}",
      "subscriptions_url": "https://api.github.com/users/charlie2233/subscriptions",
      "organizations_url": "https://api.github.com/users/charlie2233/orgs",
      "repos_url": "https://api.github.com/users/charlie2233/repos",
      "events_url": "https://api.github.com/users/charlie2233/events{/privacy}",
      "received_events_url": "https://api.github.com/users/charlie2233/received_events",
      "type": "User",
      "user_view_type": "public",
      "site_admin": false
    },
    "html_url": "https://github.com/charlie2233/newproyecto",
    "description": null,
    "fork": false,
    "url": "https://api.github.com/repos/charlie2233/newproyecto",
    "forks_url": "https://api.github.com/repos/charlie2233/newproyecto/forks",
    "keys_url": "https://api.github.com/repos/charlie2233/newproyecto/keys{/key_id}",
    "collaborators_url": "https://api.github.com/repos/charlie2233/newproyecto/collaborators{/collaborator}",
    "teams_url": "https://api.github.com/repos/charlie2233/newproyecto/teams",
    "hooks_url": "https://api.github.com/repos/charlie2233/newproyecto/hooks",
    "issue_events_url": "https://api.github.com/repos/charlie2233/newproyecto/issues/events{/number}",
    "events_url": "https://api.github.com/repos/charlie2233/newproyecto/events",
    "assignees_url": "https://api.github.com/repos/charlie2233/newproyecto/assignees{/user}",
    "branches_url": "https://api.github.com/repos/charlie2233/newproyecto/branches{/branch}",
    "tags_url": "https://api.github.com/repos/charlie2233/newproyecto/tags",
    "blobs_url": "https://api.github.com/repos/charlie2233/newproyecto/git/blobs{/sha}",
    "git_tags_url": "https://api.github.com/repos/charlie2233/newproyecto/git/tags{/sha}",
    "git_refs_url": "https://api.github.com/repos/charlie2233/newproyecto/git/refs{/sha}",
    "trees_url": "https://api.github.com/repos/charlie2233/newproyecto/git/trees{/sha}",
    "statuses_url": "https://api.github.com/repos/charlie2233/newproyecto/statuses/{sha}",
    "languages_url": "https://api.github.com/repos/charlie2233/newproyecto/languages",
    "stargazers_url": "https://api.github.com/repos/charlie2233/newproyecto/stargazers",
    "contributors_url": "https://api.github.com/repos/charlie2233/newproyecto/contributors",
    "subscribers_url": "https://api.github.com/repos/charlie2233/newproyecto/subscribers",
    "subscription_url": "https://api.github.com/repos/charlie2233/newproyecto/subscription",
    "commits_url": "https://api.github.com/repos/charlie2233/newproyecto/commits{/sha}",
    "git_commits_url": "https://api.github.com/repos/charlie2233/newproyecto/git/commits{/sha}",
    "comments_url": "https://api.github.com/repos/charlie2233/newproyecto/comments{/number}",
    "issue_comment_url": "https://api.github.com/repos/charlie2233/newproyecto/issues/comments{/number}",
    "contents_url": "https://api.github.com/repos/charlie2233/newproyecto/contents/{+path}",
    "compare_url": "https://api.github.com/repos/charlie2233/newproyecto/compare/{base}...{head}",
    "merges_url": "https://api.github.com/repos/charlie2233/newproyecto/merges",
    "archive_url": "https://api.github.com/repos/charlie2233/newproyecto/{archive_format}{/ref}",
    "downloads_url": "https://api.github.com/repos/charlie2233/newproyecto/downloads",
    "issues_url": "https://api.github.com/repos/charlie2233/newproyecto/issues{/number}",
    "pulls_url": "https://api.github.com/repos/charlie2233/newproyecto/pulls{/number}",
    "milestones_url": "https://api.github.com/repos/charlie2233/newproyecto/milestones{/number}",
    "notifications_url": "https://api.github.com/repos/charlie2233/newproyecto/notifications{?since,all,participating}",
    "labels_url": "https://api.github.com/repos/charlie2233/newproyecto/labels{/name}",
    "releases_url": "https://api.github.com/repos/charlie2233/newproyecto/releases{/id}",
    "deployments_url": "https://api.github.com/repos/charlie2233/newproyecto/deployments",
    "created_at": "2025-03-10T03:43:04Z",
    "updated_at": "2025-03-10T04:28:09Z",
    "pushed_at": "2025-03-10T04:28:06Z",
    "git_url": "git://github.com/charlie2233/newproyecto.git",
    "ssh_url": "git@github.com:charlie2233/newproyecto.git",
    "clone_url": "https://github.com/charlie2233/newproyecto.git",
    "svn_url": "https://github.com/charlie2233/newproyecto",
    "homepage": null,
    "size": 3,
    "stargazers_count": 0,
    "watchers_count": 0,
    "language": "Python",
    "has_issues": true,
    "has_projects": true,
    "has_downloads": true,
    "has_wiki": false,
    "has_pages": false,
    "has_discussions": false,
    "forks_count": 0,
    "mirror_url": null,
    "archived": false,
    "disabled": false,
    "open_issues_count": 0,
    "license": null,
    "allow_forking": true,
    "is_template": false,
    "web_commit_signoff_required": false,
    "topics": [

    ],
    "visibility": "public",
    "forks": 0,
    "open_issues": 0,
    "watchers": 0,
    "default_branch": "main",
    "permissions": {
      "admin": true,
      "maintain": true,
      "push": true,
      "triage": true,
      "pull": true
    }
  },
  {
    "id": 817989588,
    "node_id": "R_kgDOMMGH1A",
    "name": "counselorapp",
    "full_name": "charlie2233/counselorapp",
    "private": false,
    "owner": {
      "login": "charlie2233",
      "id": 117957000,
      "node_id": "U_kgDOBwfhiA",
      "avatar_url": "https://avatars.githubusercontent.com/u/117957000?v=4",
      "gravatar_id": "",
      "url": "https://api.github.com/users/charlie2233",
      "html_url": "https://github.com/charlie2233",
      "followers_url": "https://api.github.com/users/charlie2233/followers",
      "following_url": "https://api.github.com/users/charlie2233/following{/other_user}",
      "gists_url": "https://api.github.com/users/charlie2233/gists{/gist_id}",
      "starred_url": "https://api.github.com/users/charlie2233/starred{/owner}{/repo}",
      "subscriptions_url": "https://api.github.com/users/charlie2233/subscriptions",
      "organizations_url": "https://api.github.com/users/charlie2233/orgs",
      "repos_url": "https://api.github.com/users/charlie2233/repos",
      "events_url": "https://api.github.com/users/charlie2233/events{/privacy}",
      "received_events_url": "https://api.github.com/users/charlie2233/received_events",
      "type": "User",
      "user_view_type": "public",
      "site_admin": false
    },
    "html_url": "https://github.com/charlie2233/counselorapp",
    "description": null,
    "fork": false,
    "url": "https://api.github.com/repos/charlie2233/counselorapp",
    "forks_url": "https://api.github.com/repos/charlie2233/counselorapp/forks",
    "keys_url": "https://api.github.com/repos/charlie2233/counselorapp/keys{/key_id}",
    "collaborators_url": "https://api.github.com/repos/charlie2233/counselorapp/collaborators{/collaborator}",
    "teams_url": "https://api.github.com/repos/charlie2233/counselorapp/teams",
    "hooks_url": "https://api.github.com/repos/charlie2233/counselorapp/hooks",
    "issue_events_url": "https://api.github.com/repos/charlie2233/counselorapp/issues/events{/number}",
    "events_url": "https://api.github.com/repos/charlie2233/counselorapp/events",
    "assignees_url": "https://api.github.com/repos/charlie2233/counselorapp/assignees{/user}",
    "branches_url": "https://api.github.com/repos/charlie2233/counselorapp/branches{/branch}",
    "tags_url": "https://api.github.com/repos/charlie2233/counselorapp/tags",
    "blobs_url": "https://api.github.com/repos/charlie2233/counselorapp/git/blobs{/sha}",
    "git_tags_url": "https://api.github.com/repos/charlie2233/counselorapp/git/tags{/sha}",
    "git_refs_url": "https://api.github.com/repos/charlie2233/counselorapp/git/refs{/sha}",
    "trees_url": "https://api.github.com/repos/charlie2233/counselorapp/git/trees{/sha}",
    "statuses_url": "https://api.github.com/repos/charlie2233/counselorapp/statuses/{sha}",
    "languages_url": "https://api.github.com/repos/charlie2233/counselorapp/languages",
    "stargazers_url": "https://api.github.com/repos/charlie2233/counselorapp/stargazers",
    "contributors_url": "https://api.github.com/repos/charlie2233/counselorapp/contributors",
    "subscribers_url": "https://api.github.com/repos/charlie2233/counselorapp/subscribers",
    "subscription_url": "https://api.github.com/repos/charlie2233/counselorapp/subscription",
    "commits_url": "https://api.github.com/repos/charlie2233/counselorapp/commits{/sha}",
    "git_commits_url": "https://api.github.com/repos/charlie2233/counselorapp/git/commits{/sha}",
    "comments_url": "https://api.github.com/repos/charlie2233/counselorapp/comments{/number}",
    "issue_comment_url": "https://api.github.com/repos/charlie2233/counselorapp/issues/comments{/number}",
    "contents_url": "https://api.github.com/repos/charlie2233/counselorapp/contents/{+path}",
    "compare_url": "https://api.github.com/repos/charlie2233/counselorapp/compare/{base}...{head}",
    "merges_url": "https://api.github.com/repos/charlie2233/counselorapp/merges",
    "archive_url": "https://api.github.com/repos/charlie2233/counselorapp/{archive_format}{/ref}",
    "downloads_url": "https://api.github.com/repos/charlie2233/counselorapp/downloads",
    "issues_url": "https://api.github.com/repos/charlie2233/counselorapp/issues{/number}",
    "pulls_url": "https://api.github.com/repos/charlie2233/counselorapp/pulls{/number}",
    "milestones_url": "https://api.github.com/repos/charlie2233/counselorapp/milestones{/number}",
    "notifications_url": "https://api.github.com/repos/charlie2233/counselorapp/notifications{?since,all,participating}",
    "labels_url": "https://api.github.com/repos/charlie2233/counselorapp/labels{/name}",
    "releases_url": "https://api.github.com/repos/charlie2233/counselorapp/releases{/id}",
    "deployments_url": "https://api.github.com/repos/charlie2233/counselorapp/deployments",
    "created_at": "2024-06-20T21:43:04Z",
    "updated_at": "2024-06-20T21:43:08Z",
    "pushed_at": "2024-06-20T23:03:05Z",
    "git_url": "git://github.com/charlie2233/counselorapp.git",
    "ssh_url": "git@github.com:charlie2233/counselorapp.git",
    "clone_url": "https://github.com/charlie2233/counselorapp.git",
    "svn_url": "https://github.com/charlie2233/counselorapp",
    "homepage": null,
    "size": 269,
    "stargazers_count": 0,
    "watchers_count": 0,
    "language": null,
    "has_issues": true,
    "has_projects": true,
    "has_downloads": true,
    "has_wiki": true,
    "has_pages": false,
    "has_discussions": false,
    "forks_count": 0,
    "mirror_url": null,
    "archived": false,
    "disabled": false,
    "open_issues_count": 0,
    "license": null,
    "allow_forking": true,
    "is_template": false,
    "web_commit_signoff_required": false,
    "topics": [

    ],
    "visibility": "public",
    "forks": 0,
    "open_issues": 0,
    "watchers": 0,
    "default_branch": "main",
    "permissions": {
      "admin": true,
      "maintain": true,
      "push": true,
      "triage": true,
      "pull": true
    }
  }
]
